pyqttable/__init__.py
pyqttable/const.py
pyqttable/delegate.py
pyqttable/header.py
pyqttable/utils.py
pyqttable/version.py
pyqttable/column/__init__.py
pyqttable/column/align.py
pyqttable/column/default.py
pyqttable/column/filter.py
pyqttable/column/sorter.py
pyqttable/column/style.py
pyqttable/column/type.py
pyqttable/editor/__init__.py
pyqttable/editor/base.py
pyqttable/editor/dt_editor.py
pyqttable/editor/line_editor.py
pyqttable/editor/selection.py
pyqttable/widget/__init__.py
pyqttable/widget/combo_check_box.py
pyqttable/widget/filter_view.py
tests/__init__.py
tests/web_code.py
pyqttable-0.0.2.dist-info/LICENSE
pyqttable-0.0.2.dist-info/METADATA
pyqttable-0.0.2.dist-info/WHEEL
pyqttable-0.0.2.dist-info/top_level.txt
pyqttable-0.0.2.dist-info/RECORD
