Metadata-Version: 2.1
Name: pyqttable
Version: 0.0.2
Summary: A simple configurable table widget based on PyQt5 and pandas
Home-page: https://github.com/TongyanXu/pyqttable
Author: Tongyan Xu
Author-email: tyxu18@gmail.com
License: UNKNOWN
Platform: UNKNOWN
Classifier: Programming Language :: Python :: 3.7
Classifier: License :: OSI Approved :: MIT License
Classifier: Operating System :: OS Independent
